snowglobe/client/__init__.py
snowglobe/client/src/app.py
snowglobe/client/src/cli.py
snowglobe/client/src/cli_utils.py
snowglobe/client/src/config.py
snowglobe/client/src/models.py
snowglobe/client/src/project_manager.py
snowglobe/client/src/runner.py
snowglobe/client/src/stats.py
snowglobe/client/src/telemetry.py
snowglobe/client/src/types.py
snowglobe/client/src/utils.py
snowglobe-0.4.17.dist-info/licenses/LICENSE
snowglobe-0.4.17.dist-info/METADATA
snowglobe-0.4.17.dist-info/WHEEL
snowglobe-0.4.17.dist-info/entry_points.txt
snowglobe-0.4.17.dist-info/top_level.txt
snowglobe-0.4.17.dist-info/RECORD
