Metadata-Version: 2.4
Name: snowglobe
Version: 0.4.17
Summary: client server for usage with snowglobe experiments
Author-email: Guardrails AI <contact@guardrailsai.com>
License: MIT License
Requires-Python: >=3.9
License-File: LICENSE
Requires-Dist: typer>=0.9.0
Requires-Dist: fastapi>=0.115.6
Requires-Dist: uvicorn[standard]>=0.23.0
Requires-Dist: openai>=1.55.2
Requires-Dist: requests>=2.31.0
Requires-Dist: pydantic>=2.11.5
Requires-Dist: APScheduler==4.0.0a6
Requires-Dist: httpx==0.28.1
Requires-Dist: rich>=13.0.0
Provides-Extra: dev
Requires-Dist: ruff<0.2.0,>=0.1.0; extra == "dev"
Requires-Dist: mypy<2.0.0,>=1.5.0; extra == "dev"
Requires-Dist: pre-commit>=4.1.0; extra == "dev"
Requires-Dist: coverage>=7.6.12; extra == "dev"
Requires-Dist: pyright[nodejs]>=1.1.396; extra == "dev"
Dynamic: license-file
